cluster_coords/__init__.py
cluster_coords/cluster_coords.py
cluster_coords/random.py
cluster_coords-0.0.7.dist-info/LICENSE
cluster_coords-0.0.7.dist-info/METADATA
cluster_coords-0.0.7.dist-info/WHEEL
cluster_coords-0.0.7.dist-info/top_level.txt
cluster_coords-0.0.7.dist-info/RECORD
