Metadata-Version: 2.1
Name: cluster-coords
Version: 0.0.7
Summary: Build cluster from multiple identical longitude and latitude coordinates
Home-page: https://github.com/sonnyparlin/cluster_coords/
Author: Sonny Parlin
Author-email: ask@sparl.in
License: MIT
Project-URL: Bug Tracker, https://github.com/sonnyparlin/cluster_coords/issues
Platform: UNKNOWN
Classifier: Programming Language :: Python :: 3
Classifier: License :: OSI Approved :: MIT License
Classifier: Operating System :: OS Independent
Requires-Python: >=3.6
